synthplayer/__init__.py
synthplayer/oscillators.py
synthplayer/params.py
synthplayer/playback.py
synthplayer/sample.py
synthplayer/streaming.py
synthplayer/synth.py
synthplayer/soundapi/__init__.py
synthplayer/soundapi/base.py
synthplayer/soundapi/miniaudio.py
synthplayer/soundapi/soundcard.py
synthplayer/soundapi/sounddevice.py
synthplayer-2.5.dist-info/LICENSE
synthplayer-2.5.dist-info/METADATA
synthplayer-2.5.dist-info/WHEEL
synthplayer-2.5.dist-info/top_level.txt
synthplayer-2.5.dist-info/zip-safe
synthplayer-2.5.dist-info/RECORD
