Metadata-Version: 2.1
Name: synthplayer
Version: 2.5
Summary: software sound synthesizer, audio streaming and conversion, and playback engine
Home-page: https://github.com/irmen/synthesizer
Author: Irmen de Jong
Author-email: irmen@razorvine.net
License: LGPL3
Keywords: sound,audio,playback,conversion,synthesizer,FM,PWM,oscillator
Platform: UNKNOWN
Classifier: Development Status :: 5 - Production/Stable
Classifier: Intended Audience :: Developers
Classifier: License :: OSI Approved :: GNU Lesser General Public License v3 (LGPLv3)
Classifier: Natural Language :: English
Classifier: Natural Language :: Dutch
Classifier: Operating System :: OS Independent
Classifier: Programming Language :: Python
Classifier: Programming Language :: Python :: 3.5
Classifier: Programming Language :: Python :: 3.6
Classifier: Programming Language :: Python :: 3.7
Classifier: Programming Language :: Python :: 3.8
Classifier: Topic :: Multimedia :: Sound/Audio
Classifier: Topic :: Multimedia :: Sound/Audio :: Conversion
Classifier: Topic :: Multimedia :: Sound/Audio :: Mixers
Classifier: Topic :: Multimedia :: Sound/Audio :: Players
Classifier: Topic :: Multimedia :: Sound/Audio :: Sound Synthesis
